[{"__symbolic":"module","version":4,"metadata":{"MAT_MENU_SCROLL_STRATEGY":{"__symbolic":"new","expression":{"__symbolic":"reference","module":"@angular/core","name":"InjectionToken","line":45,"character":8},"arguments":["mat-menu-scroll-strategy"]},"MAT_MENU_SCROLL_STRATEGY_FACTORY":{"__symbolic":"function","parameters":["overlay"],"value":{"__symbolic":"error","message":"Lambda not supported","line":49,"character":9}},"MAT_MENU_SCROLL_STRATEGY_FACTORY_PROVIDER":{"provide":{"__symbolic":"reference","name":"MAT_MENU_SCROLL_STRATEGY"},"deps":[{"__symbolic":"reference","module":"@angular/cdk/overlay","name":"Overlay","line":55,"character":9}],"useFactory":{"__symbolic":"reference","name":"MAT_MENU_SCROLL_STRATEGY_FACTORY"}},"MENU_PANEL_TOP_PADDING":8,"MatMenuTrigger":{"__symbolic":"class","decorators":[{"__symbolic":"call","expression":{"__symbolic":"reference","module":"@angular/core","name":"Directive","line":68,"character":1},"arguments":[{"selector":"[mat-menu-trigger-for], [matMenuTriggerFor]","host":{"aria-haspopup":"true","[attr.aria-expanded]":"menuOpen || null","(mousedown)":"_handleMousedown($event)","(touchstart)":"_openedBy = \"touch\"","(keydown)":"_handleKeydown($event)","(click)":"_handleClick($event)","$quoted$":["aria-haspopup","[attr.aria-expanded]","(mousedown)","(touchstart)","(keydown)","(click)"]},"exportAs":"matMenuTrigger"}]}],"members":{"_deprecatedMatMenuTriggerFor":[{"__symbolic":"property","decorators":[{"__symbolic":"call","expression":{"__symbolic":"reference","module":"@angular/core","name":"Input","line":96,"character":3},"arguments":["mat-menu-trigger-for"]}]}],"menu":[{"__symbolic":"property","decorators":[{"__symbolic":"call","expression":{"__symbolic":"reference","module":"@angular/core","name":"Input","line":106,"character":3},"arguments":["matMenuTriggerFor"]}]}],"menuData":[{"__symbolic":"property","decorators":[{"__symbolic":"call","expression":{"__symbolic":"reference","module":"@angular/core","name":"Input","line":109,"character":3},"arguments":["matMenuTriggerData"]}]}],"menuOpened":[{"__symbolic":"property","decorators":[{"__symbolic":"call","expression":{"__symbolic":"reference","module":"@angular/core","name":"Output","line":112,"character":3}}]}],"onMenuOpen":[{"__symbolic":"property","decorators":[{"__symbolic":"call","expression":{"__symbolic":"reference","module":"@angular/core","name":"Output","line":120,"character":3}}]}],"menuClosed":[{"__symbolic":"property","decorators":[{"__symbolic":"call","expression":{"__symbolic":"reference","module":"@angular/core","name":"Output","line":123,"character":3}}]}],"onMenuClose":[{"__symbolic":"property","decorators":[{"__symbolic":"call","expression":{"__symbolic":"reference","module":"@angular/core","name":"Output","line":131,"character":3}}]}],"__ctor__":[{"__symbolic":"constructor","parameterDecorators":[null,null,null,[{"__symbolic":"call","expression":{"__symbolic":"reference","module":"@angular/core","name":"Inject","line":136,"character":15},"arguments":[{"__symbolic":"reference","name":"MAT_MENU_SCROLL_STRATEGY"}]}],[{"__symbolic":"call","expression":{"__symbolic":"reference","module":"@angular/core","name":"Optional","line":137,"character":15}}],[{"__symbolic":"call","expression":{"__symbolic":"reference","module":"@angular/core","name":"Optional","line":138,"character":15}},{"__symbolic":"call","expression":{"__symbolic":"reference","module":"@angular/core","name":"Self","line":138,"character":27}}],[{"__symbolic":"call","expression":{"__symbolic":"reference","module":"@angular/core","name":"Optional","line":139,"character":15}}],null],"parameters":[{"__symbolic":"reference","module":"@angular/cdk/overlay","name":"Overlay","line":133,"character":32},{"__symbolic":"reference","module":"@angular/core","name":"ElementRef","line":134,"character":32,"arguments":[{"__symbolic":"error","message":"Could not resolve type","line":134,"character":43,"context":{"typeName":"HTMLElement"}}]},{"__symbolic":"reference","module":"@angular/core","name":"ViewContainerRef","line":135,"character":41},{"__symbolic":"reference","name":"any"},{"__symbolic":"reference","module":"./menu-directive","name":"MatMenu","line":137,"character":47},{"__symbolic":"reference","module":"./menu-item","name":"MatMenuItem","line":138,"character":61},{"__symbolic":"reference","module":"@angular/cdk/bidi","name":"Directionality","line":139,"character":40},{"__symbolic":"reference","module":"@angular/cdk/a11y","name":"FocusMonitor","line":142,"character":38}]}],"ngAfterContentInit":[{"__symbolic":"method"}],"ngOnDestroy":[{"__symbolic":"method"}],"triggersSubmenu":[{"__symbolic":"method"}],"toggleMenu":[{"__symbolic":"method"}],"openMenu":[{"__symbolic":"method"}],"closeMenu":[{"__symbolic":"method"}],"focus":[{"__symbolic":"method"}],"_destroyMenu":[{"__symbolic":"method"}],"_initMenu":[{"__symbolic":"method"}],"_setMenuElevation":[{"__symbolic":"method"}],"_resetMenu":[{"__symbolic":"method"}],"_setIsMenuOpen":[{"__symbolic":"method"}],"_checkMenu":[{"__symbolic":"method"}],"_createOverlay":[{"__symbolic":"method"}],"_getOverlayConfig":[{"__symbolic":"method"}],"_subscribeToPositions":[{"__symbolic":"method"}],"_setPosition":[{"__symbolic":"method"}],"_cleanUpSubscriptions":[{"__symbolic":"method"}],"_menuClosingActions":[{"__symbolic":"method"}],"_handleMousedown":[{"__symbolic":"method"}],"_handleKeydown":[{"__symbolic":"method"}],"_handleClick":[{"__symbolic":"method"}],"_handleHover":[{"__symbolic":"method"}]}}},"importAs":"@angular/material/menu"}]